plutopdfkit/__init__.py
plutopdfkit-0.1.0.dist-info/METADATA
plutopdfkit-0.1.0.dist-info/WHEEL
plutopdfkit-0.1.0.dist-info/top_level.txt
plutopdfkit-0.1.0.dist-info/RECORD
