Metadata-Version: 2.1
Name: plutopdfkit
Version: 0.1.0
Summary: UNKNOWN
Home-page: UNKNOWN
Author: Samuel Ugochukwu
Author-email: sammycageagle@gmail.com
License: UNKNOWN
Platform: UNKNOWN
Classifier: Programming Language :: Python :: 3
Classifier: License :: OSI Approved :: MIT License
Classifier: Operating System :: OS Independent
Requires-Python: >=3.8
Requires-Dist: playwright
